.gitignore
CHANGES.txt
CONTRIBUTORS.txt
MANIFEST.in
README.rst
bootstrap.py
buildout.cfg
setup.py
docs/LICENSE.GPL
docs/LICENSE.txt
src/customer/__init__.py
src/customer.krainrealestate.egg-info/PKG-INFO
src/customer.krainrealestate.egg-info/SOURCES.txt
src/customer.krainrealestate.egg-info/dependency_links.txt
src/customer.krainrealestate.egg-info/entry_points.txt
src/customer.krainrealestate.egg-info/namespace_packages.txt
src/customer.krainrealestate.egg-info/not-zip-safe
src/customer.krainrealestate.egg-info/requires.txt
src/customer.krainrealestate.egg-info/top_level.txt
src/customer/krainrealestate/__init__.py
src/customer/krainrealestate/adapter.py
src/customer/krainrealestate/configure.zcml
src/customer/krainrealestate/migration.py
src/customer/krainrealestate/overrides.zcml
src/customer/krainrealestate/testing.py
src/customer/krainrealestate/userdataschema.py
src/customer/krainrealestate/browser/CustomizedUserDataPanel.py
src/customer/krainrealestate/browser/__init__.py
src/customer/krainrealestate/browser/agentprofile_viewlet.py
src/customer/krainrealestate/browser/agentsearch_viewlet.py
src/customer/krainrealestate/browser/configure.zcml
src/customer/krainrealestate/browser/interfaces.py
src/customer/krainrealestate/browser/templates/agentprofile.pt
src/customer/krainrealestate/browser/templates/agentsearch.pt
src/customer/krainrealestate/locales/customer.krainrealestate.pot
src/customer/krainrealestate/locales/de/LC_MESSAGES/customer.krainrealestate.po
src/customer/krainrealestate/locales/en/LC_MESSAGES/customer.krainrealestate.po
src/customer/krainrealestate/locales/es/LC_MESSAGES/customer.krainrealestate.po
src/customer/krainrealestate/profiles/default/actions.xml
src/customer/krainrealestate/profiles/default/browserlayer.xml
src/customer/krainrealestate/profiles/default/componentregistry.xml
src/customer/krainrealestate/profiles/default/memberdata_properties.xml
src/customer/krainrealestate/profiles/default/metadata.xml
src/customer/krainrealestate/profiles/default/propertiestool.xml
src/customer/krainrealestate/profiles/default/rolemap.xml
src/customer/krainrealestate/profiles/default/skins.xml
src/customer/krainrealestate/tests/__init__.py
src/customer/krainrealestate/tests/test_setup.py
src/customer/krainrealestate/tests/test_viewlets.py