Metadata-Version: 1.0
Name: customer.krainrealestate
Version: 0.8
Summary: Extends Plone user data for customer needs
Home-page: https://github.com/propertyshelf/customer.krainrealestate
Author: Propertyshelf, Inc.
Author-email: development@propertyshelf.com
License: gpl
Keywords: Plone Memberdata Propertyshelf
Platform: UNKNOWN
Classifier: Environment :: Web Environment
Classifier: Operating System :: OS Independent
Classifier: Framework :: Zope2
Classifier: Framework :: Plone
Classifier: Framework :: Plone :: 4.2
Classifier: Framework :: Plone :: 4.3
Classifier: Programming Language :: Python
Classifier: Programming Language :: Python :: 2.6
Classifier: Programming Language :: Python :: 2.7
Classifier: Topic :: Software Development :: Libraries :: Python Modules
